nlib.py
setup.py
nlib.egg-info/PKG-INFO
nlib.egg-info/SOURCES.txt
nlib.egg-info/dependency_links.txt
nlib.egg-info/top_level.txt