Metadata-Version: 1.0
Name: nlib
Version: 0.5
Summary: Python Library of Numerical Algorithms
Home-page: https://github.com/mdipierro/nlib
Author: Massimo DiPierro
Author-email: massimo.dipierro@gmail.com
License: BSD
Keywords: numerical
Platform: UNKNOWN
